<?xml version="1.0" encoding="utf-8"?>
<ArrayOfDungeonVo xmlns:xsi="http://www.w3.org/2001/XMLSchema-instance" xmlns:xsd="http://www.w3.org/2001/XMLSchema">
  <DungeonVo>
    <HeroVo>
      <id>1</id>
      <heroId>1</heroId>
      <camp>1</camp>
      <x>-34.19</x>
      <y>-2.94</y>
      <z>54.27</z>
      <r>406.790039</r>
    </HeroVo>
  </DungeonVo>
  <DungeonVo>
    <HeroVo>
      <id>2</id>
      <heroId>2</heroId>
      <camp>1</camp>
      <x>-32.86</x>
      <y>-2.94</y>
      <z>52.85</z>
      <r>46.79004</r>
    </HeroVo>
  </DungeonVo>
  <DungeonVo>
    <HeroVo>
      <id>3</id>
      <heroId>3</heroId>
      <camp>1</camp>
      <x>-35.66</x>
      <y>-2.94</y>
      <z>55.83</z>
      <r>46.79004</r>
    </HeroVo>
  </DungeonVo>
  <DungeonVo>
    <FlagVo>
      <id>1</id>
      <flag>2</flag>
      <x>0</x>
      <y>0</y>
      <z>0</z>
      <r>0</r>
      <width>0</width>
      <height>0</height>
      <second>0</second>
      <monster>0</monster>
      <hp>0</hp>
      <wave>0</wave>
      <monsterList>
        <DungeonMonsterlVo>
          <id>1</id>
          <actId>110101101</actId>
          <camp>2</camp>
          <actFlag>1</actFlag>
          <x>-18.62</x>
          <y>-2.94</y>
          <z>63.33</z>
          <r>231.452316</r>
          <actNum>1</actNum>
          <randRadius>0</randRadius>
          <trigger>0</trigger>
          <modelName />
          <delay>0</delay>
        </DungeonMonsterlVo>
        <DungeonMonsterlVo>
          <id>2</id>
          <actId>110101101</actId>
          <camp>2</camp>
          <actFlag>1</actFlag>
          <x>-19.67</x>
          <y>-2.94</y>
          <z>64.65</z>
          <r>-128.547638</r>
          <actNum>1</actNum>
          <randRadius>0</randRadius>
          <trigger>0</trigger>
          <modelName />
          <delay>0</delay>
        </DungeonMonsterlVo>
        <DungeonMonsterlVo>
          <id>3</id>
          <actId>110101101</actId>
          <camp>2</camp>
          <actFlag>1</actFlag>
          <x>-20.75</x>
          <y>-2.94</y>
          <z>66</z>
          <r>-128.547638</r>
          <actNum>1</actNum>
          <randRadius>0</randRadius>
          <trigger>0</trigger>
          <modelName />
          <delay>0</delay>
        </DungeonMonsterlVo>
        <DungeonMonsterlVo>
          <id>4</id>
          <actId>110101102</actId>
          <camp>2</camp>
          <actFlag>1</actFlag>
          <x>-19.26</x>
          <y>-2.94</y>
          <z>67.19</z>
          <r>231.452377</r>
          <actNum>1</actNum>
          <randRadius>0</randRadius>
          <trigger>0</trigger>
          <modelName />
          <delay>0</delay>
        </DungeonMonsterlVo>
        <DungeonMonsterlVo>
          <id>5</id>
          <actId>110101102</actId>
          <camp>2</camp>
          <actFlag>1</actFlag>
          <x>-17.05</x>
          <y>-2.94</y>
          <z>64.42</z>
          <r>-128.547638</r>
          <actNum>1</actNum>
          <randRadius>0</randRadius>
          <trigger>0</trigger>
          <modelName />
          <delay>0</delay>
        </DungeonMonsterlVo>
        <DungeonMonsterlVo>
          <id>6</id>
          <actId>110101102</actId>
          <camp>2</camp>
          <actFlag>1</actFlag>
          <x>-18.16</x>
          <y>-2.94</y>
          <z>65.8</z>
          <r>-128.547638</r>
          <actNum>1</actNum>
          <randRadius>0</randRadius>
          <trigger>0</trigger>
          <modelName />
          <delay>0</delay>
        </DungeonMonsterlVo>
        <DungeonMonsterlVo>
          <id>7</id>
          <actId>110101103</actId>
          <camp>2</camp>
          <actFlag>1</actFlag>
          <x>-15.69</x>
          <y>-2.94</y>
          <z>65.51</z>
          <r>231.452377</r>
          <actNum>1</actNum>
          <randRadius>0</randRadius>
          <trigger>0</trigger>
          <modelName />
          <delay>0</delay>
        </DungeonMonsterlVo>
        <DungeonMonsterlVo>
          <id>8</id>
          <actId>110101103</actId>
          <camp>2</camp>
          <actFlag>1</actFlag>
          <x>-17.91</x>
          <y>-2.94</y>
          <z>68.3</z>
          <r>-128.547638</r>
          <actNum>1</actNum>
          <randRadius>0</randRadius>
          <trigger>0</trigger>
          <modelName />
          <delay>0</delay>
        </DungeonMonsterlVo>
        <DungeonMonsterlVo>
          <id>9</id>
          <actId>110101103</actId>
          <camp>2</camp>
          <actFlag>1</actFlag>
          <x>-16.85</x>
          <y>-2.94</y>
          <z>66.96</z>
          <r>-128.547638</r>
          <actNum>1</actNum>
          <randRadius>0</randRadius>
          <trigger>0</trigger>
          <modelName />
          <delay>0</delay>
        </DungeonMonsterlVo>
      </monsterList>
    </FlagVo>
  </DungeonVo>
  <DungeonVo>
    <FlagVo>
      <id>2</id>
      <flag>4</flag>
      <x>0</x>
      <y>0</y>
      <z>0</z>
      <r>0</r>
      <width>0</width>
      <height>0</height>
      <second>0</second>
      <monster>0</monster>
      <hp>0</hp>
      <wave>1</wave>
      <monsterList>
        <DungeonMonsterlVo>
          <id>1</id>
          <actId>110101104</actId>
          <camp>2</camp>
          <actFlag>2</actFlag>
          <x>8.22</x>
          <y>-2.9</y>
          <z>73.74</z>
          <r>297.673584</r>
          <actNum>1</actNum>
          <randRadius>0</randRadius>
          <trigger>0</trigger>
          <modelName />
          <delay>0</delay>
        </DungeonMonsterlVo>
        <DungeonMonsterlVo>
          <id>2</id>
          <actId>110101104</actId>
          <camp>2</camp>
          <actFlag>2</actFlag>
          <x>6.43</x>
          <y>-2.9</y>
          <z>70.34</z>
          <r>-62.3264465</r>
          <actNum>1</actNum>
          <randRadius>0</randRadius>
          <trigger>0</trigger>
          <modelName />
          <delay>0</delay>
        </DungeonMonsterlVo>
        <DungeonMonsterlVo>
          <id>3</id>
          <actId>110101104</actId>
          <camp>2</camp>
          <actFlag>2</actFlag>
          <x>7.32</x>
          <y>-2.9</y>
          <z>72.03</z>
          <r>-62.3264465</r>
          <actNum>1</actNum>
          <randRadius>0</randRadius>
          <trigger>0</trigger>
          <modelName />
          <delay>0</delay>
        </DungeonMonsterlVo>
        <DungeonMonsterlVo>
          <id>4</id>
          <actId>110101105</actId>
          <camp>2</camp>
          <actFlag>2</actFlag>
          <x>8.23</x>
          <y>-2.9</y>
          <z>69.4</z>
          <r>297.673584</r>
          <actNum>1</actNum>
          <randRadius>0</randRadius>
          <trigger>0</trigger>
          <modelName />
          <delay>0</delay>
        </DungeonMonsterlVo>
        <DungeonMonsterlVo>
          <id>5</id>
          <actId>110101105</actId>
          <camp>2</camp>
          <actFlag>2</actFlag>
          <x>10.01</x>
          <y>-2.9</y>
          <z>72.79</z>
          <r>-62.3264465</r>
          <actNum>1</actNum>
          <randRadius>0</randRadius>
          <trigger>0</trigger>
          <modelName />
          <delay>0</delay>
        </DungeonMonsterlVo>
        <DungeonMonsterlVo>
          <id>6</id>
          <actId>110101105</actId>
          <camp>2</camp>
          <actFlag>2</actFlag>
          <x>9.13</x>
          <y>-2.9</y>
          <z>71.11</z>
          <r>-62.3264465</r>
          <actNum>1</actNum>
          <randRadius>0</randRadius>
          <trigger>0</trigger>
          <modelName />
          <delay>0</delay>
        </DungeonMonsterlVo>
        <DungeonMonsterlVo>
          <id>7</id>
          <actId>110101106</actId>
          <camp>2</camp>
          <actFlag>2</actFlag>
          <x>11.74</x>
          <y>-2.9</y>
          <z>71.88</z>
          <r>297.673584</r>
          <actNum>1</actNum>
          <randRadius>0</randRadius>
          <trigger>0</trigger>
          <modelName />
          <delay>0</delay>
        </DungeonMonsterlVo>
        <DungeonMonsterlVo>
          <id>8</id>
          <actId>110101106</actId>
          <camp>2</camp>
          <actFlag>2</actFlag>
          <x>10.78</x>
          <y>-2.9</y>
          <z>70.06</z>
          <r>-62.3264465</r>
          <actNum>1</actNum>
          <randRadius>0</randRadius>
          <trigger>0</trigger>
          <modelName />
          <delay>0</delay>
        </DungeonMonsterlVo>
        <DungeonMonsterlVo>
          <id>9</id>
          <actId>110101106</actId>
          <camp>2</camp>
          <actFlag>2</actFlag>
          <x>9.84</x>
          <y>-2.9</y>
          <z>68.47</z>
          <r>-62.3264465</r>
          <actNum>1</actNum>
          <randRadius>0</randRadius>
          <trigger>0</trigger>
          <modelName />
          <delay>0</delay>
        </DungeonMonsterlVo>
        <DungeonMonsterlVo>
          <id>10</id>
          <actId>110101107</actId>
          <camp>2</camp>
          <actFlag>2</actFlag>
          <x>12.89</x>
          <y>-2.9</y>
          <z>69.45</z>
          <r>297.673584</r>
          <actNum>1</actNum>
          <randRadius>0</randRadius>
          <trigger>0</trigger>
          <modelName />
          <delay>0</delay>
        </DungeonMonsterlVo>
      </monsterList>
    </FlagVo>
  </DungeonVo>
  <DungeonVo>
    <FlagVo>
      <id>3</id>
      <flag>4</flag>
      <x>0</x>
      <y>0</y>
      <z>0</z>
      <r>0</r>
      <width>0</width>
      <height>0</height>
      <second>0</second>
      <monster>0</monster>
      <hp>0</hp>
      <wave>2</wave>
      <monsterList>
        <DungeonMonsterlVo>
          <id>1</id>
          <actId>110101108</actId>
          <camp>2</camp>
          <actFlag>3</actFlag>
          <x>31.98</x>
          <y>-2.48</y>
          <z>51.76</z>
          <r>326.638367</r>
          <actNum>1</actNum>
          <randRadius>0</randRadius>
          <trigger>0</trigger>
          <modelName />
          <delay>0</delay>
        </DungeonMonsterlVo>
        <DungeonMonsterlVo>
          <id>2</id>
          <actId>110101108</actId>
          <camp>2</camp>
          <actFlag>3</actFlag>
          <x>35.9</x>
          <y>-2.48</y>
          <z>54.34</z>
          <r>-33.3616638</r>
          <actNum>1</actNum>
          <randRadius>0</randRadius>
          <trigger>0</trigger>
          <modelName />
          <delay>0</delay>
        </DungeonMonsterlVo>
        <DungeonMonsterlVo>
          <id>3</id>
          <actId>110101108</actId>
          <camp>2</camp>
          <actFlag>3</actFlag>
          <x>34.56</x>
          <y>-2.48</y>
          <z>53.46</z>
          <r>-33.3616638</r>
          <actNum>1</actNum>
          <randRadius>0</randRadius>
          <trigger>0</trigger>
          <modelName />
          <delay>0</delay>
        </DungeonMonsterlVo>
        <DungeonMonsterlVo>
          <id>4</id>
          <actId>110101108</actId>
          <camp>2</camp>
          <actFlag>3</actFlag>
          <x>33.29</x>
          <y>-2.48</y>
          <z>52.63</z>
          <r>-33.3616638</r>
          <actNum>1</actNum>
          <randRadius>0</randRadius>
          <trigger>0</trigger>
          <modelName />
          <delay>0</delay>
        </DungeonMonsterlVo>
        <DungeonMonsterlVo>
          <id>5</id>
          <actId>110101109</actId>
          <camp>2</camp>
          <actFlag>3</actFlag>
          <x>32.84</x>
          <y>-2.48</y>
          <z>50.47</z>
          <r>326.638367</r>
          <actNum>1</actNum>
          <randRadius>0</randRadius>
          <trigger>0</trigger>
          <modelName />
          <delay>0</delay>
        </DungeonMonsterlVo>
        <DungeonMonsterlVo>
          <id>6</id>
          <actId>110101109</actId>
          <camp>2</camp>
          <actFlag>3</actFlag>
          <x>36.7</x>
          <y>-2.48</y>
          <z>53.01</z>
          <r>-33.3616638</r>
          <actNum>1</actNum>
          <randRadius>0</randRadius>
          <trigger>0</trigger>
          <modelName />
          <delay>0</delay>
        </DungeonMonsterlVo>
        <DungeonMonsterlVo>
          <id>7</id>
          <actId>110101109</actId>
          <camp>2</camp>
          <actFlag>3</actFlag>
          <x>35.46</x>
          <y>-2.48</y>
          <z>52.19</z>
          <r>-33.3616638</r>
          <actNum>1</actNum>
          <randRadius>0</randRadius>
          <trigger>0</trigger>
          <modelName />
          <delay>0</delay>
        </DungeonMonsterlVo>
        <DungeonMonsterlVo>
          <id>8</id>
          <actId>110101109</actId>
          <camp>2</camp>
          <actFlag>3</actFlag>
          <x>34.22</x>
          <y>-2.48</y>
          <z>51.38</z>
          <r>-33.3616638</r>
          <actNum>1</actNum>
          <randRadius>0</randRadius>
          <trigger>0</trigger>
          <modelName />
          <delay>0</delay>
        </DungeonMonsterlVo>
        <DungeonMonsterlVo>
          <id>9</id>
          <actId>110101110</actId>
          <camp>2</camp>
          <actFlag>3</actFlag>
          <x>37</x>
          <y>-1.36</y>
          <z>49.77</z>
          <r>326.6384</r>
          <actNum>1</actNum>
          <randRadius>1</randRadius>
          <trigger>0</trigger>
          <modelName />
          <delay>0</delay>
        </DungeonMonsterlVo>
      </monsterList>
    </FlagVo>
  </DungeonVo>
  <DungeonVo>
    <FlagVo>
      <id>4</id>
      <flag>4</flag>
      <x>0</x>
      <y>0</y>
      <z>0</z>
      <r>0</r>
      <width>0</width>
      <height>0</height>
      <second>0</second>
      <monster>0</monster>
      <hp>0</hp>
      <wave>3</wave>
      <monsterList>
        <DungeonMonsterlVo>
          <id>1</id>
          <actId>110101111</actId>
          <camp>2</camp>
          <actFlag>4</actFlag>
          <x>69.05</x>
          <y>1.09</y>
          <z>52.23</z>
          <r>236.754044</r>
          <actNum>1</actNum>
          <randRadius>0</randRadius>
          <trigger>0</trigger>
          <modelName />
          <delay>0</delay>
        </DungeonMonsterlVo>
        <DungeonMonsterlVo>
          <id>2</id>
          <actId>110101111</actId>
          <camp>2</camp>
          <actFlag>4</actFlag>
          <x>65.86</x>
          <y>1.08</y>
          <z>56.96</z>
          <r>-123.245972</r>
          <actNum>1</actNum>
          <randRadius>0</randRadius>
          <trigger>0</trigger>
          <modelName />
          <delay>0</delay>
        </DungeonMonsterlVo>
        <DungeonMonsterlVo>
          <id>3</id>
          <actId>110101111</actId>
          <camp>2</camp>
          <actFlag>4</actFlag>
          <x>66.95</x>
          <y>1.08</y>
          <z>55.43</z>
          <r>-123.245972</r>
          <actNum>1</actNum>
          <randRadius>0</randRadius>
          <trigger>0</trigger>
          <modelName />
          <delay>0</delay>
        </DungeonMonsterlVo>
        <DungeonMonsterlVo>
          <id>4</id>
          <actId>110101111</actId>
          <camp>2</camp>
          <actFlag>4</actFlag>
          <x>67.96</x>
          <y>1.09</y>
          <z>53.89</z>
          <r>-123.245972</r>
          <actNum>1</actNum>
          <randRadius>0</randRadius>
          <trigger>0</trigger>
          <modelName />
          <delay>0</delay>
        </DungeonMonsterlVo>
        <DungeonMonsterlVo>
          <id>5</id>
          <actId>110101112</actId>
          <camp>2</camp>
          <actFlag>4</actFlag>
          <x>68.06</x>
          <y>1.08</y>
          <z>56.89</z>
          <r>236.754028</r>
          <actNum>1</actNum>
          <randRadius>0</randRadius>
          <trigger>0</trigger>
          <modelName />
          <delay>0</delay>
        </DungeonMonsterlVo>
        <DungeonMonsterlVo>
          <id>6</id>
          <actId>110101112</actId>
          <camp>2</camp>
          <actFlag>4</actFlag>
          <x>68.99</x>
          <y>1.08</y>
          <z>55.47</z>
          <r>-123.245972</r>
          <actNum>1</actNum>
          <randRadius>0</randRadius>
          <trigger>0</trigger>
          <modelName />
          <delay>0</delay>
        </DungeonMonsterlVo>
        <DungeonMonsterlVo>
          <id>7</id>
          <actId>110101112</actId>
          <camp>2</camp>
          <actFlag>4</actFlag>
          <x>69.92</x>
          <y>1.08</y>
          <z>54.04</z>
          <r>-123.245972</r>
          <actNum>1</actNum>
          <randRadius>0</randRadius>
          <trigger>0</trigger>
          <modelName />
          <delay>0</delay>
        </DungeonMonsterlVo>
        <DungeonMonsterlVo>
          <id>8</id>
          <actId>110101112</actId>
          <camp>2</camp>
          <actFlag>4</actFlag>
          <x>67.06</x>
          <y>1.08</y>
          <z>58.41</z>
          <r>-123.245972</r>
          <actNum>1</actNum>
          <randRadius>0</randRadius>
          <trigger>0</trigger>
          <modelName />
          <delay>0</delay>
        </DungeonMonsterlVo>
        <DungeonMonsterlVo>
          <id>9</id>
          <actId>110101112</actId>
          <camp>2</camp>
          <actFlag>4</actFlag>
          <x>70.83</x>
          <y>1.08</y>
          <z>52.65</z>
          <r>-123.245972</r>
          <actNum>1</actNum>
          <randRadius>0</randRadius>
          <trigger>0</trigger>
          <modelName />
          <delay>0</delay>
        </DungeonMonsterlVo>
        <DungeonMonsterlVo>
          <id>10</id>
          <actId>110101113</actId>
          <camp>2</camp>
          <actFlag>4</actFlag>
          <x>72</x>
          <y>1.09</y>
          <z>56.54</z>
          <r>236.754028</r>
          <actNum>1</actNum>
          <randRadius>0</randRadius>
          <trigger>0</trigger>
          <modelName />
          <delay>0</delay>
        </DungeonMonsterlVo>
        <DungeonMonsterlVo>
          <id>11</id>
          <actId>110101114</actId>
          <camp>2</camp>
          <actFlag>4</actFlag>
          <x>70.52</x>
          <y>1.09</y>
          <z>58.75</z>
          <r>236.754028</r>
          <actNum>1</actNum>
          <randRadius>0</randRadius>
          <trigger>0</trigger>
          <modelName />
          <delay>0</delay>
        </DungeonMonsterlVo>
      </monsterList>
    </FlagVo>
  </DungeonVo>
  <DungeonVo>
    <DoorVo>
      <id>1</id>
      <type>2</type>
      <flag>1</flag>
      <close>0</close>
      <name>TX_door_11</name>
      <x>-13.3126831</x>
      <y>-2.522134</y>
      <z>73.3579</z>
      <r>55.3394852</r>
      <width>18</width>
      <height>1</height>
      <doorType>0</doorType>
    </DoorVo>
  </DungeonVo>
  <DungeonVo>
    <DoorVo>
      <id>2</id>
      <type>2</type>
      <flag>3</flag>
      <close>0</close>
      <name>TX_door_10</name>
      <x>41.1424561</x>
      <y>1.467866</y>
      <z>42.53512</z>
      <r>325.339539</r>
      <width>18</width>
      <height>1</height>
      <doorType>0</doorType>
    </DoorVo>
  </DungeonVo>
  <DungeonVo>
    <DoorVo>
      <id>3</id>
      <type>1</type>
      <flag>4</flag>
      <close>0</close>
      <name>TX_door_8</name>
      <x>49.4859</x>
      <y>1.467866</y>
      <z>41.0681458</z>
      <r>55.3395424</r>
      <width>18</width>
      <height>1</height>
      <doorType>0</doorType>
    </DoorVo>
  </DungeonVo>
  <DungeonVo>
    <PortalVo>
      <id>1</id>
      <type>1</type>
      <flag>1</flag>
      <close>0</close>
      <x>0</x>
      <y>0</y>
      <z>0</z>
      <r>0</r>
      <width>0</width>
      <height>0</height>
      <target_x>-16.85</target_x>
      <target_y>-2.94</target_y>
      <target_z>66.96</target_z>
      <target_r>0</target_r>
      <target_type>1</target_type>
    </PortalVo>
  </DungeonVo>
  <DungeonVo>
    <PortalVo>
      <id>2</id>
      <type>2</type>
      <flag>1</flag>
      <close>0</close>
      <x>0</x>
      <y>0</y>
      <z>0</z>
      <r>0</r>
      <width>0</width>
      <height>0</height>
      <target_x>12.89</target_x>
      <target_y>-2.9</target_y>
      <target_z>69.45</target_z>
      <target_r>0</target_r>
      <target_type>1</target_type>
    </PortalVo>
  </DungeonVo>
  <DungeonVo>
    <PortalVo>
      <id>3</id>
      <type>2</type>
      <flag>2</flag>
      <close>0</close>
      <x>0</x>
      <y>0</y>
      <z>0</z>
      <r>0</r>
      <width>0</width>
      <height>0</height>
      <target_x>37</target_x>
      <target_y>-1.36</target_y>
      <target_z>49.77</target_z>
      <target_r>0</target_r>
      <target_type>1</target_type>
    </PortalVo>
  </DungeonVo>
  <DungeonVo>
    <PortalVo>
      <id>4</id>
      <type>2</type>
      <flag>3</flag>
      <close>0</close>
      <x>0</x>
      <y>0</y>
      <z>0</z>
      <r>0</r>
      <width>0</width>
      <height>0</height>
      <target_x>72</target_x>
      <target_y>1.09</target_y>
      <target_z>56.54</target_z>
      <target_r>0</target_r>
      <target_type>1</target_type>
    </PortalVo>
  </DungeonVo>
</ArrayOfDungeonVo>